[{
  "_id": {
    "$oid": "63307e99d6dfba2a806711b0"
  },
  "name": "Node.js",
  "createdAt": {
    "$date": {
      "$numberLong": "1664122521888"
    }
  },
  "updatedAt": {
    "$date": {
      "$numberLong": "1664122542270"
    }
  },
  "__v": 0
},{
  "_id": {
    "$oid": "63307f31d6dfba2a806711b8"
  },
  "name": "PHP",
  "createdAt": {
    "$date": {
      "$numberLong": "1664122673120"
    }
  },
  "updatedAt": {
    "$date": {
      "$numberLong": "1664122673120"
    }
  },
  "__v": 0
},{
  "_id": {
    "$oid": "63307f3bd6dfba2a806711bb"
  },
  "name": "Javascript",
  "createdAt": {
    "$date": {
      "$numberLong": "1664122683894"
    }
  },
  "updatedAt": {
    "$date": {
      "$numberLong": "1664122683894"
    }
  },
  "__v": 0
},{
  "_id": {
    "$oid": "63307f47d6dfba2a806711be"
  },
  "name": "React.js",
  "createdAt": {
    "$date": {
      "$numberLong": "1664122695839"
    }
  },
  "updatedAt": {
    "$date": {
      "$numberLong": "1664122695839"
    }
  },
  "__v": 0
},{
  "_id": {
    "$oid": "63313c284268d422f864b13a"
  },
  "name": "Python",
  "createdAt": {
    "$date": {
      "$numberLong": "1664171048085"
    }
  },
  "updatedAt": {
    "$date": {
      "$numberLong": "1664171048085"
    }
  },
  "__v": 0
},{
  "_id": {
    "$oid": "63536270ca93590004df962a"
  },
  "name": "science",
  "createdAt": {
    "$date": {
      "$numberLong": "1666409072032"
    }
  },
  "updatedAt": {
    "$date": {
      "$numberLong": "1666409072032"
    }
  },
  "__v": 0
}]